CHANGES.txt
MANIFEST.in
README.rst
rtd.txt
setup.cfg
setup.py
tox.ini
docs/.gitignore
docs/Makefile
docs/api.rst
docs/conf.py
docs/index.rst
kemmering/__init__.py
kemmering/html.py
kemmering.egg-info/PKG-INFO
kemmering.egg-info/SOURCES.txt
kemmering.egg-info/dependency_links.txt
kemmering.egg-info/not-zip-safe
kemmering.egg-info/requires.txt
kemmering.egg-info/top_level.txt